agenty/__init__.py
agenty/agent.py
agenty/decorators.py
agenty/exceptions.py
agenty/pipeline.py
agenty/protocol.py
agenty/py.typed
agenty/template.py
agenty/types.py
agenty/components/__init__.py
agenty/components/memory.py
agenty/components/usage.py
agenty/integrations/__init__.py
agenty/integrations/smol/__init__.py
agenty/integrations/smol/code_agent.py
agenty-0.1.6.dist-info/METADATA
agenty-0.1.6.dist-info/WHEEL
agenty-0.1.6.dist-info/licenses/LICENSE
agenty-0.1.6.dist-info/RECORD
