Metadata-Version: 2.4
Name: agenty
Version: 0.1.6
Summary: A framework for creating AI agents.
Author-email: Jonathan Chun <git@jonathanchun.com>
License-Expression: MIT
License-File: LICENSE
Requires-Python: <4.0,>=3.12
Requires-Dist: jinja2<4,>=3.1.5
Requires-Dist: mcp>=1.2.1
Requires-Dist: openai<2.0.0,>=1.60.2
Requires-Dist: pydantic-ai<0.0.22,>=0.0.21
Requires-Dist: rich<14.0.0,>=13.9.4
Provides-Extra: adapters
Requires-Dist: smolagents[litellm]<2,>=1.7.0; extra == 'adapters'
Provides-Extra: smol
Requires-Dist: smolagents[litellm]<2,>=1.7.0; extra == 'smol'
